README.rst
setup.py
./pytest_boost_xml/__init__.py
./pytest_boost_xml/boost_xml_log.py
./pytest_boost_xml/boost_xml_plugin.py
./pytest_boost_xml/boost_xml_report.py
./pytest_boost_xml/plugin_register.py
./pytest_boost_xml/xsl/atkFileSystem.sh
./pytest_boost_xml/xsl/convertBoostXmlToHtml.xsl
./pytest_boost_xml/xsl/convertBoostXmlToTxt.xsl
./pytest_boost_xml/xsl/generateReport.sh
./pytest_boost_xml/xsl/reportUnitTest.sh
pytest_boost_xml.egg-info/PKG-INFO
pytest_boost_xml.egg-info/SOURCES.txt
pytest_boost_xml.egg-info/dependency_links.txt
pytest_boost_xml.egg-info/entry_points.txt
pytest_boost_xml.egg-info/requires.txt
pytest_boost_xml.egg-info/top_level.txt