Metadata-Version: 2.1
Name: pytest-boost-xml
Version: 1.0
Summary: Plugin for pytest to generate boost xml reports
Home-page: http://sourceforge.net/projects/agglo/
Author: toubab
Author-email: eti.laurent@gmail.com
Classifier: Programming Language :: Python
Classifier: Programming Language :: Python :: 3
Classifier: Programming Language :: Python :: 3.5
Classifier: Programming Language :: Python :: 3.6
Classifier: Programming Language :: Python :: 3.7
Classifier: Programming Language :: Python :: 3.8
Classifier: Programming Language :: Python :: 3 :: Only
Classifier: Operating System :: POSIX :: Linux
Classifier: Development Status :: 4 - Beta
Classifier: Topic :: Software Development :: Testing
Classifier: Topic :: Software Development :: Quality Assurance
Classifier: Intended Audience :: Developers
Classifier: Framework :: Pytest
Classifier: Environment :: Console
Classifier: Natural Language :: English
